{"id": "KKV8N0TLAP6UB", "name": "tb_image_share_1594047317053", "size": 371794, "btime": 1612708175613, "mtime": 1595056994657, "ext": "jpg", "tags": ["project files"], "folders": ["KKV8N0S6WNSEY"], "isDeleted": false, "url": "", "annotation": "", "modificationTime": 1612708175600, "noThumbnail": true, "width": 750, "height": 750, "lastModified": 1710253329234, "palettes": [{"color": [228, 227, 226], "ratio": 48, "$$hashKey": "object:17782"}, {"color": [49, 47, 60], "ratio": 30, "$$hashKey": "object:17787"}, {"color": [98, 98, 126], "ratio": 5, "$$hashKey": "object:17786"}, {"color": [140, 131, 141], "ratio": 5, "$$hashKey": "object:17788"}, {"color": [179, 173, 174], "ratio": 4.95, "$$hashKey": "object:17789"}, {"color": [193, 168, 144], "ratio": 3.06, "$$hashKey": "object:17783"}, {"color": [153, 120, 98], "ratio": 0.94, "$$hashKey": "object:17784"}, {"color": [155, 156, 160], "ratio": 0.66, "$$hashKey": "object:17785"}]}